pymangle/__init__.py
pymangle/_mangle.c
pymangle/_mangle.cpython-312-darwin.so
pymangle/cap.c
pymangle/cap.h
pymangle/defs.h
pymangle/mangle.c
pymangle/mangle.h
pymangle/mangle.py
pymangle/pixel.c
pymangle/pixel.h
pymangle/point.c
pymangle/point.h
pymangle/polygon.c
pymangle/polygon.h
pymangle/rand.c
pymangle/rand.h
pymangle/stack.c
pymangle/stack.h
pymangle/test.py
pymangle/version.py
sdss_pymangle-0.9.3.dist-info/METADATA
sdss_pymangle-0.9.3.dist-info/WHEEL
sdss_pymangle-0.9.3.dist-info/top_level.txt
sdss_pymangle-0.9.3.dist-info/RECORD
